{
  "annotations": {
    "list": [
      {
        "builtIn": 1,
        "datasource": {
          "type": "grafana",
          "uid": "-- Grafana --"
        },
        "enable": true,
        "hide": true,
        "iconColor": "rgba(0, 211, 255, 1)",
        "name": "Annotations & Alerts",
        "type": "dashboard"
      }
    ]
  },
  "description": "Measuring performance of request/response nwaku protocols.\nLightpush, Filter and Store request processing times are measured.",
  "editable": true,
  "fiscalYearStartMonth": 0,
  "graphTooltip": 0,
  "id": 2,
  "links": [],
  "panels": [
    {
      "collapsed": false,
      "gridPos": {
        "h": 1,
        "w": 24,
        "x": 0,
        "y": 0
      },
      "id": 9,
      "panels": [],
      "title": "Lightpush / Filter",
      "type": "row"
    },
    {
      "datasource": {
        "type": "prometheus",
        "uid": "PBFA97CFB590B2093"
      },
      "fieldConfig": {
        "defaults": {
          "custom": {
            "hideFrom": {
              "legend": false,
              "tooltip": false,
              "viz": false
            },
            "scaleDistribution": {
              "type": "linear"
            }
          }
        },
        "overrides": []
      },
      "gridPos": {
        "h": 8,
        "w": 12,
        "x": 0,
        "y": 1
      },
      "id": 1,
      "options": {
        "calculate": false,
        "cellGap": 1,
        "color": {
          "exponent": 0.5,
          "fill": "dark-orange",
          "mode": "scheme",
          "reverse": true,
          "scale": "exponential",
          "scheme": "Reds",
          "steps": 64
        },
        "exemplars": {
          "color": "rgba(255,0,255,0.7)"
        },
        "filterValues": {
          "le": 1e-9
        },
        "legend": {
          "show": true
        },
        "rowsFrame": {
          "layout": "auto"
        },
        "tooltip": {
          "mode": "single",
          "showColorScale": false,
          "yHistogram": false
        },
        "yAxis": {
          "axisPlacement": "left",
          "reverse": false,
          "unit": "s"
        }
      },
      "pluginVersion": "11.5.2",
      "targets": [
        {
          "datasource": {
            "type": "prometheus",
            "uid": "PBFA97CFB590B2093"
          },
          "disableTextWrap": false,
          "editorMode": "code",
          "exemplar": false,
          "expr": "sum by(le) (increase(waku_service_request_handling_duration_seconds_bucket{instance=\"servicenode:8008\", service=\"/vac/waku/lightpush/2.0.0-beta1\"}[$__rate_interval]))",
          "format": "heatmap",
          "fullMetaSearch": false,
          "includeNullMetadata": true,
          "instant": false,
          "interval": "",
          "legendFormat": "{{le}}",
          "range": true,
          "refId": "A",
          "useBackend": false
        }
      ],
      "title": "Lightpush request performance",
      "type": "heatmap"
    },
    {
      "datasource": {
        "type": "prometheus",
        "uid": "PBFA97CFB590B2093"
      },
      "fieldConfig": {
        "defaults": {
          "color": {
            "mode": "palette-classic"
          },
          "custom": {
            "axisBorderShow": false,
            "axisCenteredZero": false,
            "axisColorMode": "text",
            "axisLabel": "",
            "axisPlacement": "auto",
            "barAlignment": 0,
            "barWidthFactor": 0.6,
            "drawStyle": "line",
            "fillOpacity": 0,
            "gradientMode": "none",
            "hideFrom": {
              "legend": false,
              "tooltip": false,
              "viz": false
            },
            "insertNulls": false,
            "lineInterpolation": "linear",
            "lineWidth": 1,
            "pointSize": 5,
            "scaleDistribution": {
              "type": "linear"
            },
            "showPoints": "auto",
            "spanNulls": false,
            "stacking": {
              "group": "A",
              "mode": "none"
            },
            "thresholdsStyle": {
              "mode": "off"
            }
          },
          "mappings": [],
          "thresholds": {
            "mode": "absolute",
            "steps": [
              {
                "color": "green",
                "value": null
              },
              {
                "color": "red",
                "value": 80
              }
            ]
          }
        },
        "overrides": []
      },
      "gridPos": {
        "h": 8,
        "w": 12,
        "x": 12,
        "y": 1
      },
      "id": 11,
      "options": {
        "legend": {
          "calcs": [],
          "displayMode": "list",
          "placement": "bottom",
          "showLegend": true
        },
        "tooltip": {
          "hideZeros": false,
          "mode": "single",
          "sort": "none"
        }
      },
      "pluginVersion": "11.5.2",
      "targets": [
        {
          "editorMode": "builder",
          "expr": "rate(waku_service_requests_total{service = \"/vac/waku/lightpush/2.0.0-beta1\", instance=\"servicenode:8008\"}[$__rate_interval])",
          "legendFormat": "{{service}}",
          "range": true,
          "refId": "A"
        },
        {
          "datasource": {
            "type": "prometheus",
            "uid": "PBFA97CFB590B2093"
          },
          "disableTextWrap": false,
          "editorMode": "builder",
          "expr": "rate(waku_service_requests_total{service=\"/vac/waku/filter-subscribe/2.0.0-beta1\", instance=\"servicenode:8008\"}[$__rate_interval])",
          "fullMetaSearch": false,
          "hide": false,
          "includeNullMetadata": true,
          "legendFormat": "{{service}}",
          "range": true,
          "refId": "B",
          "useBackend": false
        }
      ],
      "title": "Lightpush and filter request rate",
      "type": "timeseries"
    },
    {
      "datasource": {
        "type": "prometheus",
        "uid": "PBFA97CFB590B2093"
      },
      "fieldConfig": {
        "defaults": {
          "custom": {
            "hideFrom": {
              "legend": false,
              "tooltip": false,
              "viz": false
            },
            "scaleDistribution": {
              "type": "linear"
            }
          }
        },
        "overrides": []
      },
      "gridPos": {
        "h": 8,
        "w": 12,
        "x": 0,
        "y": 9
      },
      "id": 2,
      "options": {
        "calculate": false,
        "cellGap": 1,
        "color": {
          "exponent": 0.5,
          "fill": "dark-orange",
          "mode": "scheme",
          "reverse": true,
          "scale": "exponential",
          "scheme": "Reds",
          "steps": 64
        },
        "exemplars": {
          "color": "rgba(255,0,255,0.7)"
        },
        "filterValues": {
          "le": 1e-9
        },
        "legend": {
          "show": true
        },
        "rowsFrame": {
          "layout": "auto"
        },
        "tooltip": {
          "mode": "single",
          "showColorScale": false,
          "yHistogram": false
        },
        "yAxis": {
          "axisPlacement": "left",
          "reverse": false,
          "unit": "s"
        }
      },
      "pluginVersion": "11.5.2",
      "targets": [
        {
          "datasource": {
            "type": "prometheus",
            "uid": "PBFA97CFB590B2093"
          },
          "disableTextWrap": false,
          "editorMode": "builder",
          "expr": "sum by(le) (increase(waku_service_request_handling_duration_seconds_bucket{instance=\"servicenode:8008\", service=\"/vac/waku/filter-subscribe/2.0.0-beta1\"}[$__rate_interval]))",
          "format": "heatmap",
          "fullMetaSearch": false,
          "includeNullMetadata": true,
          "legendFormat": "{{le}}",
          "range": true,
          "refId": "A",
          "useBackend": false
        }
      ],
      "title": "Filter subscribe performance",
      "type": "heatmap"
    },
    {
      "datasource": {
        "type": "prometheus",
        "uid": "PBFA97CFB590B2093"
      },
      "fieldConfig": {
        "defaults": {
          "custom": {
            "hideFrom": {
              "legend": false,
              "tooltip": false,
              "viz": false
            },
            "scaleDistribution": {
              "type": "linear"
            }
          }
        },
        "overrides": []
      },
      "gridPos": {
        "h": 8,
        "w": 12,
        "x": 12,
        "y": 9
      },
      "id": 4,
      "options": {
        "calculate": false,
        "cellGap": 1,
        "color": {
          "exponent": 0.5,
          "fill": "dark-orange",
          "mode": "scheme",
          "reverse": true,
          "scale": "exponential",
          "scheme": "Reds",
          "steps": 64
        },
        "exemplars": {
          "color": "rgba(255,0,255,0.7)"
        },
        "filterValues": {
          "le": 1e-9
        },
        "legend": {
          "show": true
        },
        "rowsFrame": {
          "layout": "auto"
        },
        "tooltip": {
          "mode": "single",
          "showColorScale": false,
          "yHistogram": false
        },
        "yAxis": {
          "axisPlacement": "left",
          "reverse": false,
          "unit": "s"
        }
      },
      "pluginVersion": "11.5.2",
      "targets": [
        {
          "datasource": {
            "type": "prometheus",
            "uid": "PBFA97CFB590B2093"
          },
          "disableTextWrap": false,
          "editorMode": "builder",
          "expr": "sum by(le) (increase(waku_filter_handle_message_duration_seconds_bucket{instance=\"servicenode:8008\"}[$__rate_interval]))",
          "format": "heatmap",
          "fullMetaSearch": false,
          "includeNullMetadata": true,
          "legendFormat": "{{le}}",
          "range": true,
          "refId": "A",
          "useBackend": false
        }
      ],
      "title": "Filter message handling performance",
      "type": "heatmap"
    },
    {
      "collapsed": false,
      "gridPos": {
        "h": 1,
        "w": 24,
        "x": 0,
        "y": 17
      },
      "id": 8,
      "panels": [],
      "title": "General load",
      "type": "row"
    },
    {
      "datasource": {
        "type": "prometheus",
        "uid": "PBFA97CFB590B2093"
      },
      "fieldConfig": {
        "defaults": {
          "color": {
            "mode": "palette-classic"
          },
          "custom": {
            "axisBorderShow": false,
            "axisCenteredZero": false,
            "axisColorMode": "text",
            "axisLabel": "",
            "axisPlacement": "auto",
            "barAlignment": 0,
            "barWidthFactor": 0.6,
            "drawStyle": "line",
            "fillOpacity": 0,
            "gradientMode": "none",
            "hideFrom": {
              "legend": false,
              "tooltip": false,
              "viz": false
            },
            "insertNulls": false,
            "lineInterpolation": "linear",
            "lineWidth": 1,
            "pointSize": 5,
            "scaleDistribution": {
              "type": "linear"
            },
            "showPoints": "auto",
            "spanNulls": false,
            "stacking": {
              "group": "A",
              "mode": "none"
            },
            "thresholdsStyle": {
              "mode": "off"
            }
          },
          "mappings": [],
          "thresholds": {
            "mode": "absolute",
            "steps": [
              {
                "color": "green",
                "value": null
              },
              {
                "color": "red",
                "value": 80
              }
            ]
          },
          "unit": "Bps"
        },
        "overrides": []
      },
      "gridPos": {
        "h": 8,
        "w": 12,
        "x": 0,
        "y": 18
      },
      "id": 6,
      "options": {
        "legend": {
          "calcs": [],
          "displayMode": "list",
          "placement": "bottom",
          "showLegend": true
        },
        "tooltip": {
          "hideZeros": false,
          "mode": "single",
          "sort": "none"
        }
      },
      "pluginVersion": "11.5.2",
      "targets": [
        {
          "disableTextWrap": false,
          "editorMode": "builder",
          "expr": "rate(libp2p_network_bytes_total{instance=\"servicenode:8008\"}[$__rate_interval])",
          "fullMetaSearch": false,
          "includeNullMetadata": true,
          "legendFormat": "{{direction}}",
          "range": true,
          "refId": "A",
          "useBackend": false
        }
      ],
      "title": "Libp2p traffic",
      "type": "timeseries"
    },
    {
      "datasource": {
        "type": "prometheus",
        "uid": "PBFA97CFB590B2093"
      },
      "fieldConfig": {
        "defaults": {
          "color": {
            "mode": "palette-classic"
          },
          "custom": {
            "axisBorderShow": false,
            "axisCenteredZero": false,
            "axisColorMode": "text",
            "axisLabel": "",
            "axisPlacement": "auto",
            "barAlignment": 0,
            "barWidthFactor": 0.6,
            "drawStyle": "line",
            "fillOpacity": 0,
            "gradientMode": "none",
            "hideFrom": {
              "legend": false,
              "tooltip": false,
              "viz": false
            },
            "insertNulls": false,
            "lineInterpolation": "linear",
            "lineWidth": 1,
            "pointSize": 5,
            "scaleDistribution": {
              "type": "linear"
            },
            "showPoints": "auto",
            "spanNulls": false,
            "stacking": {
              "group": "A",
              "mode": "none"
            },
            "thresholdsStyle": {
              "mode": "off"
            }
          },
          "mappings": [],
          "thresholds": {
            "mode": "absolute",
            "steps": [
              {
                "color": "green",
                "value": null
              },
              {
                "color": "red",
                "value": 80
              }
            ]
          },
          "unit": "percentunit"
        },
        "overrides": []
      },
      "gridPos": {
        "h": 8,
        "w": 12,
        "x": 12,
        "y": 18
      },
      "id": 14,
      "options": {
        "legend": {
          "calcs": [],
          "displayMode": "list",
          "placement": "bottom",
          "showLegend": true
        },
        "tooltip": {
          "hideZeros": false,
          "mode": "single",
          "sort": "none"
        }
      },
      "pluginVersion": "11.5.2",
      "targets": [
        {
          "editorMode": "code",
          "expr": "rate(container_cpu_usage_seconds_total{container_label_com_docker_compose_service=\"servicenode\"}[$__rate_interval])",
          "legendFormat": "{{container_label_com_docker_compose_service}}",
          "range": true,
          "refId": "A"
        }
      ],
      "title": "CPU usage",
      "type": "timeseries"
    },
    {
      "datasource": {
        "type": "prometheus",
        "uid": "PBFA97CFB590B2093"
      },
      "fieldConfig": {
        "defaults": {
          "color": {
            "mode": "palette-classic"
          },
          "custom": {
            "axisBorderShow": false,
            "axisCenteredZero": false,
            "axisColorMode": "text",
            "axisGridShow": true,
            "axisLabel": "",
            "axisPlacement": "auto",
            "barAlignment": 0,
            "barWidthFactor": 0.6,
            "drawStyle": "line",
            "fillOpacity": 27,
            "gradientMode": "opacity",
            "hideFrom": {
              "legend": false,
              "tooltip": false,
              "viz": false
            },
            "insertNulls": false,
            "lineInterpolation": "linear",
            "lineStyle": {
              "fill": "solid"
            },
            "lineWidth": 1,
            "pointSize": 5,
            "scaleDistribution": {
              "type": "linear"
            },
            "showPoints": "auto",
            "spanNulls": false,
            "stacking": {
              "group": "A",
              "mode": "none"
            },
            "thresholdsStyle": {
              "mode": "off"
            }
          },
          "mappings": [],
          "thresholds": {
            "mode": "absolute",
            "steps": [
              {
                "color": "green",
                "value": null
              },
              {
                "color": "red",
                "value": 80
              }
            ]
          },
          "unit": "decbytes"
        },
        "overrides": []
      },
      "gridPos": {
        "h": 8,
        "w": 12,
        "x": 0,
        "y": 26
      },
      "id": 7,
      "options": {
        "legend": {
          "calcs": [
            "lastNotNull"
          ],
          "displayMode": "list",
          "placement": "bottom",
          "showLegend": true
        },
        "tooltip": {
          "hideZeros": false,
          "mode": "single",
          "sort": "none"
        }
      },
      "pluginVersion": "11.5.2",
      "targets": [
        {
          "datasource": {
            "type": "prometheus",
            "uid": "PBFA97CFB590B2093"
          },
          "disableTextWrap": false,
          "editorMode": "code",
          "exemplar": false,
          "expr": "container_memory_usage_bytes{container_label_com_docker_compose_service=\"servicenode\"}",
          "format": "time_series",
          "fullMetaSearch": false,
          "hide": false,
          "includeNullMetadata": true,
          "instant": false,
          "legendFormat": "{{container_label_com_docker_compose_service}}",
          "range": true,
          "refId": "B",
          "useBackend": false
        }
      ],
      "title": "Container memory usage",
      "type": "timeseries"
    },
    {
      "datasource": {
        "type": "prometheus",
        "uid": "PBFA97CFB590B2093"
      },
      "fieldConfig": {
        "defaults": {
          "color": {
            "mode": "palette-classic"
          },
          "custom": {
            "axisBorderShow": false,
            "axisCenteredZero": false,
            "axisColorMode": "text",
            "axisLabel": "",
            "axisPlacement": "auto",
            "barAlignment": 0,
            "barWidthFactor": 0.6,
            "drawStyle": "line",
            "fillOpacity": 25,
            "gradientMode": "opacity",
            "hideFrom": {
              "legend": false,
              "tooltip": false,
              "viz": false
            },
            "insertNulls": false,
            "lineInterpolation": "linear",
            "lineWidth": 1,
            "pointSize": 5,
            "scaleDistribution": {
              "type": "linear"
            },
            "showPoints": "auto",
            "spanNulls": false,
            "stacking": {
              "group": "A",
              "mode": "none"
            },
            "thresholdsStyle": {
              "mode": "off"
            }
          },
          "mappings": [],
          "thresholds": {
            "mode": "absolute",
            "steps": [
              {
                "color": "green",
                "value": null
              },
              {
                "color": "red",
                "value": 80
              }
            ]
          },
          "unit": "decbytes"
        },
        "overrides": []
      },
      "gridPos": {
        "h": 8,
        "w": 12,
        "x": 12,
        "y": 26
      },
      "id": 5,
      "options": {
        "legend": {
          "calcs": [
            "lastNotNull"
          ],
          "displayMode": "table",
          "placement": "right",
          "showLegend": true
        },
        "tooltip": {
          "hideZeros": false,
          "mode": "single",
          "sort": "none"
        }
      },
      "pluginVersion": "11.5.2",
      "targets": [
        {
          "disableTextWrap": false,
          "editorMode": "builder",
          "expr": "nim_gc_mem_bytes{instance=\"$nwaku_instance\"}",
          "format": "time_series",
          "fullMetaSearch": false,
          "includeNullMetadata": true,
          "legendFormat": "Nim gc mem bytes of {{instance}}",
          "range": true,
          "refId": "A",
          "useBackend": false
        },
        {
          "datasource": {
            "type": "prometheus",
            "uid": "PBFA97CFB590B2093"
          },
          "disableTextWrap": false,
          "editorMode": "builder",
          "expr": "nim_gc_mem_occupied_bytes{instance=\"servicenode:8008\"}",
          "fullMetaSearch": false,
          "hide": false,
          "includeNullMetadata": true,
          "instant": false,
          "legendFormat": "Nim gc occupied bytes of {{instance}}",
          "range": true,
          "refId": "B",
          "useBackend": false
        },
        {
          "datasource": {
            "type": "prometheus",
            "uid": "PBFA97CFB590B2093"
          },
          "disableTextWrap": false,
          "editorMode": "builder",
          "expr": "nim_gc_heap_instance_occupied_summed_bytes{instance=\"servicenode:8008\"}",
          "fullMetaSearch": false,
          "hide": false,
          "includeNullMetadata": true,
          "instant": false,
          "legendFormat": "Nim gc heap bytes of {{instance}}",
          "range": true,
          "refId": "C",
          "useBackend": false
        },
        {
          "datasource": {
            "type": "prometheus",
            "uid": "PBFA97CFB590B2093"
          },
          "disableTextWrap": false,
          "editorMode": "builder",
          "expr": "process_virtual_memory_bytes{instance=\"servicenode:8008\"}",
          "fullMetaSearch": false,
          "hide": false,
          "includeNullMetadata": true,
          "instant": false,
          "legendFormat": "Process virtual memory of {{instance}}",
          "range": true,
          "refId": "D",
          "useBackend": false
        }
      ],
      "title": "NIM GC Memory",
      "type": "timeseries"
    },
    {
      "collapsed": true,
      "gridPos": {
        "h": 1,
        "w": 24,
        "x": 0,
        "y": 34
      },
      "id": 10,
      "panels": [
        {
          "datasource": {
            "type": "prometheus",
            "uid": "PBFA97CFB590B2093"
          },
          "fieldConfig": {
            "defaults": {
              "custom": {
                "hideFrom": {
                  "legend": false,
                  "tooltip": false,
                  "viz": false
                },
                "scaleDistribution": {
                  "type": "linear"
                }
              }
            },
            "overrides": []
          },
          "gridPos": {
            "h": 8,
            "w": 12,
            "x": 0,
            "y": 34
          },
          "id": 3,
          "options": {
            "calculate": false,
            "cellGap": 1,
            "color": {
              "exponent": 0.5,
              "fill": "dark-orange",
              "mode": "scheme",
              "reverse": true,
              "scale": "exponential",
              "scheme": "Reds",
              "steps": 64
            },
            "exemplars": {
              "color": "rgba(255,0,255,0.7)"
            },
            "filterValues": {
              "le": 1e-9
            },
            "legend": {
              "show": true
            },
            "rowsFrame": {
              "layout": "auto"
            },
            "tooltip": {
              "mode": "single",
              "showColorScale": false,
              "yHistogram": false
            },
            "yAxis": {
              "axisPlacement": "left",
              "reverse": false,
              "unit": "s"
            }
          },
          "pluginVersion": "11.5.2",
          "targets": [
            {
              "datasource": {
                "type": "prometheus",
                "uid": "PBFA97CFB590B2093"
              },
              "disableTextWrap": false,
              "editorMode": "code",
              "expr": "sum by(le) (increase(waku_service_request_handling_duration_seconds_bucket{instance=\"servicenode:8008\", service=\"/vac/waku/store-query/3.0.0\"}[$__rate_interval]))",
              "format": "heatmap",
              "fullMetaSearch": false,
              "includeNullMetadata": true,
              "legendFormat": "{{le}}",
              "range": true,
              "refId": "A",
              "useBackend": false
            }
          ],
          "title": "Store query performance",
          "type": "heatmap"
        },
        {
          "datasource": {
            "type": "prometheus",
            "uid": "PBFA97CFB590B2093"
          },
          "fieldConfig": {
            "defaults": {
              "color": {
                "mode": "palette-classic"
              },
              "custom": {
                "axisBorderShow": false,
                "axisCenteredZero": false,
                "axisColorMode": "text",
                "axisLabel": "",
                "axisPlacement": "auto",
                "barAlignment": 0,
                "barWidthFactor": 0.6,
                "drawStyle": "line",
                "fillOpacity": 0,
                "gradientMode": "none",
                "hideFrom": {
                  "legend": false,
                  "tooltip": false,
                  "viz": false
                },
                "insertNulls": false,
                "lineInterpolation": "linear",
                "lineWidth": 1,
                "pointSize": 5,
                "scaleDistribution": {
                  "type": "linear"
                },
                "showPoints": "auto",
                "spanNulls": false,
                "stacking": {
                  "group": "A",
                  "mode": "none"
                },
                "thresholdsStyle": {
                  "mode": "off"
                }
              },
              "mappings": [],
              "thresholds": {
                "mode": "absolute",
                "steps": [
                  {
                    "color": "green",
                    "value": null
                  },
                  {
                    "color": "red",
                    "value": 80
                  }
                ]
              }
            },
            "overrides": []
          },
          "gridPos": {
            "h": 8,
            "w": 12,
            "x": 12,
            "y": 34
          },
          "id": 12,
          "options": {
            "legend": {
              "calcs": [],
              "displayMode": "list",
              "placement": "bottom",
              "showLegend": true
            },
            "tooltip": {
              "hideZeros": false,
              "mode": "single",
              "sort": "none"
            }
          },
          "pluginVersion": "11.5.2",
          "targets": [
            {
              "disableTextWrap": false,
              "editorMode": "builder",
              "expr": "rate(waku_service_requests_total{service=\"/vac/waku/store-query/3.0.0\", instance=\"servicenode:8008\"}[$__rate_interval])",
              "fullMetaSearch": false,
              "includeNullMetadata": true,
              "legendFormat": "{{service}}",
              "range": true,
              "refId": "A",
              "useBackend": false
            }
          ],
          "title": "Store request rate",
          "type": "timeseries"
        }
      ],
      "title": "Store",
      "type": "row"
    }
  ],
  "preload": false,
  "refresh": "",
  "schemaVersion": 40,
  "tags": [],
  "templating": {
    "list": [
      {
        "allowCustomValue": false,
        "current": {
          "text": "servicenode:8008",
          "value": "servicenode:8008"
        },
        "definition": "label_values(libp2p_peers{instance=\"servicenode:8008\"},instance)",
        "label": "nwaku-instance",
        "name": "nwaku_instance",
        "options": [],
        "query": {
          "qryType": 1,
          "query": "label_values(libp2p_peers{instance=\"servicenode:8008\"},instance)",
          "refId": "PrometheusVariableQueryEditor-VariableQuery"
        },
        "refresh": 1,
        "regex": "",
        "type": "query"
      }
    ]
  },
  "time": {
    "from": "now-6h",
    "to": "now"
  },
  "timepicker": {},
  "timezone": "browser",
  "title": "Non-relay (req/resp) protocol performance",
  "uid": "cegfnbzrn2yv4c",
  "version": 1,
  "weekStart": ""
}